{
  "formatVersion": 1,
  "database": {
    "version": 1,
    "identityHash": "57cb5857f817a269b068e71842e1a22d",
    "entities": [
      {
        "tableName": "author",
        "createSql": "CREATE TABLE IF NOT EXISTS `${TABLE_NAME}` (`id` INTEGER NOT NULL, `name` TEXT NOT NULL, `userName` TEXT NOT NULL, `email` TEXT NOT NULL, `avatarUrl` TEXT NOT NULL, `lat` TEXT NOT NULL, PRIMARY KEY(`id`))",
        "fields": [
          {
            "fieldPath": "id",
            "columnName": "id",
            "affinity": "INTEGER",
            "notNull": true
          },
          {
            "fieldPath": "name",
            "columnName": "name",
            "affinity": "TEXT",
            "notNull": true
          },
          {
            "fieldPath": "userName",
            "columnName": "userName",
            "affinity": "TEXT",
            "notNull": true
          },
          {
            "fieldPath": "email",
            "columnName": "email",
            "affinity": "TEXT",
            "notNull": true
          },
          {
            "fieldPath": "avatarUrl",
            "columnName": "avatarUrl",
            "affinity": "TEXT",
            "notNull": true
          },
          {
            "fieldPath": "lat",
            "columnName": "lat",
            "affinity": "TEXT",
            "notNull": true
          }
        ],
        "primaryKey": {
          "columnNames": [
            "id"
          ],
          "autoGenerate": false
        },
        "indices": [],
        "foreignKeys": []
      },
      {
        "tableName": "post",
        "createSql": "CREATE TABLE IF NOT EXISTS `${TABLE_NAME}` (`id` INTEGER NOT NULL, `date` TEXT NOT NULL, `title` TEXT NOT NULL, `body` TEXT NOT NULL, `imageUrl` TEXT NOT NULL, `authorId` INTEGER NOT NULL, PRIMARY KEY(`id`))",
        "fields": [
          {
            "fieldPath": "id",
            "columnName": "id",
            "affinity": "INTEGER",
            "notNull": true
          },
          {
            "fieldPath": "date",
            "columnName": "date",
            "affinity": "TEXT",
            "notNull": true
          },
          {
            "fieldPath": "title",
            "columnName": "title",
            "affinity": "TEXT",
            "notNull": true
          },
          {
            "fieldPath": "body",
            "columnName": "body",
            "affinity": "TEXT",
            "notNull": true
          },
          {
            "fieldPath": "imageUrl",
            "columnName": "imageUrl",
            "affinity": "TEXT",
            "notNull": true
          },
          {
            "fieldPath": "authorId",
            "columnName": "authorId",
            "affinity": "INTEGER",
            "notNull": true
          }
        ],
        "primaryKey": {
          "columnNames": [
            "id"
          ],
          "autoGenerate": false
        },
        "indices": [],
        "foreignKeys": []
      }
    ],
    "views": [],
    "setupQueries": [
      "CREATE TABLE IF NOT EXISTS room_master_table (id INTEGER PRIMARY KEY,identity_hash TEXT)",
      "INSERT OR REPLACE INTO room_master_table (id,identity_hash) VALUES(42, '57cb5857f817a269b068e71842e1a22d')"
    ]
  }
}